[
  {
    "id": "019f4694-7483-4b2b-964a-a5c247b28d37",
    "firstName": "Lloyd",
    "lastName": "Goyette",
    "email": "johnnie.feest@hotmail.com",
    "countryCode": 11,
    "password": "n5zrRHz20mrH1aq",
    "phoneNumber": "175278734",
    "street": "671 Rath Divide Apt. 807",
    "city": "Adamscester",
    "state": "New York",
    "postalCode": "70768",
    "country": "Canada",
    "dateOfBirth": "1964-12-31",
    "day": 12,
    "month": "October",
    "gender": "female",
    "status": "active",
    "company": "Towne and Sons"
  },
  {
    "id": "1fd82e48-e60a-403b-bdb8-69231cd80bc1",
    "firstName": "Brendan",
    "lastName": "Robel",
    "email": "ressie.willms@hotmail.com",
    "countryCode": 16,
    "password": "0ZL_hxkERWsN603",
    "phoneNumber": "932400201",
    "street": "7505 George Street Suite 910",
    "city": "East Leopoldostead",
    "state": "Minnesota",
    "postalCode": "93896-8251",
    "country": "India",
    "dateOfBirth": "1972-04-28",
    "day": 12,
    "month": "October",
    "gender": "male",
    "status": "active",
    "company": "Will Group"
  },
  {
    "id": "9e03a8a6-fcd7-43f9-966c-5c22fbbaa508",
    "firstName": "Frank",
    "lastName": "Reilly",
    "email": "ludwig96@gmail.com",
    "countryCode": 18,
    "password": "DwcbvhX5rFEKcDn",
    "phoneNumber": "109040395",
    "street": "8370 Grange Close Suite 991",
    "city": "Rogers",
    "state": "Vermont",
    "postalCode": "23862",
    "country": "Canada",
    "dateOfBirth": "1985-08-30",
    "day": 12,
    "month": "October",
    "gender": "female",
    "status": "inactive",
    "company": "Schuppe LLC"
  },
  {
    "id": "ef2df53f-8545-4e5d-a300-d42f96e2de8a",
    "firstName": "Lonnie",
    "lastName": "Heidenreich",
    "email": "eliseo_bins@hotmail.com",
    "countryCode": 11,
    "password": "duBxGktIh08o6ZY",
    "phoneNumber": "034281573",
    "street": "186 Maple Avenue Apt. 303",
    "city": "South Jackie",
    "state": "Washington",
    "postalCode": "58380-7664",
    "country": "Australia",
    "dateOfBirth": "1955-04-23",
    "day": 12,
    "month": "October",
    "gender": "male",
    "status": "inactive",
    "company": "Dicki - Christiansen"
  },
  {
    "id": "2d33f862-ae68-4945-a88a-ad590e56a1da",
    "firstName": "Felix",
    "lastName": "Cassin-Koelpin",
    "email": "berenice_fay35@yahoo.com",
    "countryCode": 12,
    "password": "Qb5UTAuuyvsKFTr",
    "phoneNumber": "984314079",
    "street": "429 The Square Apt. 709",
    "city": "Muncie",
    "state": "Missouri",
    "postalCode": "88766",
    "country": "India",
    "dateOfBirth": "2003-08-23",
    "day": 12,
    "month": "October",
    "gender": "female",
    "status": "active",
    "company": "Bogisich - Kihn"
  },
  {
    "id": "063247e0-5e25-4ac9-8636-e80c3379e564",
    "firstName": "Alexander",
    "lastName": "Schiller",
    "email": "delfina_tremblay76@gmail.com",
    "countryCode": 22,
    "password": "TIZMn0v3vm7OHQY",
    "phoneNumber": "904525782",
    "street": "43216 Carole Inlet Apt. 378",
    "city": "Kautzerburgh",
    "state": "Alaska",
    "postalCode": "06622-0430",
    "country": "Australia",
    "dateOfBirth": "1983-01-30",
    "day": 12,
    "month": "October",
    "gender": "male",
    "status": "active",
    "company": "Osinski, Schuster and Reynolds"
  },
  {
    "id": "0582bd89-e070-4ceb-9fb1-7ddc04f4909b",
    "firstName": "Marshall",
    "lastName": "Mills",
    "email": "eleanora.goodwin@yahoo.com",
    "countryCode": 3,
    "password": "NZIMZJOcMCtejui",
    "phoneNumber": "448117355",
    "street": "8255 Mosciski Ways Apt. 957",
    "city": "New Murlfield",
    "state": "Illinois",
    "postalCode": "96015",
    "country": "Israel",
    "dateOfBirth": "1960-09-07",
    "day": 12,
    "month": "October",
    "gender": "female",
    "status": "active",
    "company": "Wolff - Leannon"
  },
  {
    "id": "c5323eca-e7d8-46c8-80fa-e18cb3073f03",
    "firstName": "Theodore",
    "lastName": "Emard-Hessel",
    "email": "elisha_okeefe43@yahoo.com",
    "countryCode": 3,
    "password": "j0E69QCpzo3lsy0",
    "phoneNumber": "542355985",
    "street": "4097 Shania Gateway Suite 136",
    "city": "Lake Hannaton",
    "state": "West Virginia",
    "postalCode": "19402",
    "country": "New Zealand",
    "dateOfBirth": "1993-09-23",
    "day": 12,
    "month": "October",
    "gender": "male",
    "status": "inactive",
    "company": "MacGyver Inc"
  },
  {
    "id": "f17cf678-0f7c-4eda-8e3e-5616ac40e615",
    "firstName": "Willie",
    "lastName": "Johns",
    "email": "darron_lehner@yahoo.com",
    "countryCode": 11,
    "password": "u6BZqRWCJQEVvAw",
    "phoneNumber": "400935904",
    "street": "8392 S Bridge Street Suite 947",
    "city": "Trantowboro",
    "state": "Connecticut",
    "postalCode": "80330",
    "country": "Australia",
    "dateOfBirth": "1991-01-07",
    "day": 12,
    "month": "October",
    "gender": "male",
    "status": "inactive",
    "company": "Hane - Nicolas"
  },
  {
    "id": "90152f0b-ed38-4831-b642-70794e042696",
    "firstName": "Glen",
    "lastName": "Bernhard",
    "email": "giuseppe.johnson@hotmail.com",
    "countryCode": 15,
    "password": "scwsriFZbeZeyrs",
    "phoneNumber": "608102776",
    "street": "9224 Graham Run Apt. 901",
    "city": "North Eloyville",
    "state": "New Jersey",
    "postalCode": "73287-4502",
    "country": "Canada",
    "dateOfBirth": "1969-11-19",
    "day": 12,
    "month": "October",
    "gender": "male",
    "status": "inactive",
    "company": "Weissnat Inc"
  },
  {
    "id": "ec7c40f9-6805-4faf-804b-294d544fc097",
    "firstName": "Rolando",
    "lastName": "Johnston",
    "email": "thomas.toy47@yahoo.com",
    "countryCode": 24,
    "password": "R2mFRjvwFhZWCzA",
    "phoneNumber": "529777867",
    "street": "19457 Collins Islands Apt. 198",
    "city": "Palatine",
    "state": "Wisconsin",
    "postalCode": "04797",
    "country": "Singapore",
    "dateOfBirth": "1952-03-16",
    "day": 12,
    "month": "October",
    "gender": "female",
    "status": "active",
    "company": "Koch - Gutkowski"
  }
]